[
  { "id": "home", "match": "^/$", "pageFamily": "homepage", "heroTier": "tier1", "classificationSource": "explicit" },
  { "id": "tools-actual-detail", "match": "^/tools/[^/]+(?:/.*)?$", "pageFamily": "tool-detail", "heroTier": "tier3", "classificationSource": "pattern" },
  { "id": "tools-detail", "match": "^/tools/\\[slug\\](?:/.*)?$", "pageFamily": "tool-detail", "heroTier": "tier3", "classificationSource": "pattern" },
  { "id": "tools", "match": "^/tools(?:/.*)?$", "pageFamily": "tools", "heroTier": "tier1", "classificationSource": "explicit" },
  { "id": "glossary-actual-term", "match": "^/glossary/[^/]+(?:/.*)?$", "pageFamily": "glossary-term", "heroTier": "tier3", "classificationSource": "pattern" },
  { "id": "glossary-term", "match": "^/glossary/\\[slug\\](?:/.*)?$", "pageFamily": "glossary-term", "heroTier": "tier3", "classificationSource": "pattern" },
  { "id": "glossary", "match": "^/glossary(?:/.*)?$", "pageFamily": "glossary", "heroTier": "tier1", "classificationSource": "explicit" },
  { "id": "regulation-actual-detail", "match": "^/regulations/[^/]+(?:/.*)?$", "pageFamily": "regulation-detail", "heroTier": "tier3", "classificationSource": "pattern" },
  { "id": "regulation-detail", "match": "^/regulations/\\[[^/]+\\](?:/.*)?$", "pageFamily": "regulation-detail", "heroTier": "tier3", "classificationSource": "pattern" },
  { "id": "regulations", "match": "^/regulations(?:/.*)?$", "pageFamily": "regulations", "heroTier": "tier1", "classificationSource": "explicit" },
  { "id": "training-actual-detail", "match": "^/training/[^/]+(?:/.*)?$", "pageFamily": "training-detail", "heroTier": "tier3", "classificationSource": "pattern" },
  { "id": "training-detail", "match": "^/training/\\[[^/]+\\](?:/.*)?$", "pageFamily": "training-detail", "heroTier": "tier3", "classificationSource": "pattern" },
  { "id": "training", "match": "^/training(?:/.*)?$", "pageFamily": "training", "heroTier": "tier1", "classificationSource": "explicit" },
  { "id": "directory-actual-profile", "match": "^/directory/(profile|dossier)/[^/]+(?:/.*)?$", "pageFamily": "profile", "heroTier": "tier3", "classificationSource": "pattern" },
  { "id": "directory-profile", "match": "^/directory/(profile|dossier)/\\[[^/]+\\](?:/.*)?$", "pageFamily": "profile", "heroTier": "tier3", "classificationSource": "pattern" },
  { "id": "directory-category", "match": "^/directory/category(?:/.*)?$", "pageFamily": "directory-category", "heroTier": "tier2", "classificationSource": "pattern" },
  { "id": "directory-country-city", "match": "^/directory/\\[country\\]/\\[slug\\](?:/.*)?$", "pageFamily": "city", "heroTier": "tier2", "classificationSource": "pattern" },
  { "id": "directory-country", "match": "^/directory/\\[country\\](?:/.*)?$", "pageFamily": "country", "heroTier": "tier2", "classificationSource": "pattern" },
  { "id": "directory", "match": "^/directory(?:/.*)?$", "pageFamily": "directory", "heroTier": "tier1", "classificationSource": "explicit" },
  { "id": "corridor-actual-detail", "match": "^/corridors/[^/]+(?:/.*)?$", "pageFamily": "corridor", "heroTier": "tier3", "classificationSource": "pattern" },
  { "id": "corridor-detail", "match": "^/corridors/\\[[^/]+\\](?:/.*)?$", "pageFamily": "corridor", "heroTier": "tier3", "classificationSource": "pattern" },
  { "id": "corridors", "match": "^/corridors(?:/.*)?$", "pageFamily": "corridor", "heroTier": "tier1", "classificationSource": "explicit" },
  { "id": "route-intel", "match": "^/(corridor|map|routeintel|route-intel)(?:/.*)?$", "pageFamily": "route-intel", "heroTier": "tier1", "classificationSource": "pattern" },
  { "id": "load-detail", "match": "^/(load-board|loads)/\\[[^/]+\\](?:/.*)?$", "pageFamily": "load-detail", "heroTier": "tier3", "classificationSource": "pattern" },
  { "id": "load-board", "match": "^/(load-board|loads|jobs|available-now|backhauls)(?:/.*)?$", "pageFamily": "load-board", "heroTier": "tier1", "classificationSource": "pattern" },
  { "id": "geo-country", "match": "^/\\[country\\]$", "pageFamily": "country", "heroTier": "tier1", "classificationSource": "pattern" },
  { "id": "geo-region", "match": "^/\\[country\\]/\\[state\\]$", "pageFamily": "region", "heroTier": "tier2", "classificationSource": "pattern" },
  { "id": "geo-corridor", "match": "^/\\[country\\]/\\[state\\]/\\[corridor\\]$", "pageFamily": "corridor", "heroTier": "tier3", "classificationSource": "pattern" },
  { "id": "near-city", "match": "^/(near|near-me)(?:/.*)?$", "pageFamily": "city", "heroTier": "tier2", "classificationSource": "pattern" },
  { "id": "roles", "match": "^/roles(?:/.*)?$", "pageFamily": "role", "heroTier": "tier2", "classificationSource": "pattern" },
  { "id": "rates-market-data", "match": "^/(rates|data-products|market-data|market|reports)(?:/.*)?$", "pageFamily": "market-data", "heroTier": "tier2", "classificationSource": "pattern" },
  { "id": "sponsor", "match": "^/(sponsor|advertise)(?:/.*)?$", "pageFamily": "sponsor", "heroTier": "tier1", "classificationSource": "pattern" },
  { "id": "claim", "match": "^/(claim|onboarding/claim)(?:/.*)?$", "pageFamily": "claim", "heroTier": "tier4", "classificationSource": "pattern" },
  { "id": "pricing", "match": "^/(pricing|pro|products)(?:/.*)?$", "pageFamily": "pricing", "heroTier": "tier1", "classificationSource": "pattern" },
  { "id": "profile", "match": "^/(profile|report-card|place|operator)(?:/.*)?$", "pageFamily": "profile", "heroTier": "tier3", "classificationSource": "pattern" },
  { "id": "services-infrastructure", "match": "^/(services|infrastructure|ports|resources|forms)(?:/.*)?$", "pageFamily": "service", "heroTier": "tier2", "classificationSource": "pattern" },
  { "id": "admin", "match": "^/admin(?:/.*)?$", "pageFamily": "admin", "heroTier": "tier4", "classificationSource": "pattern" },
  { "id": "dashboard", "match": "^/(dashboard|app|broker|settings|account|community)(?:/.*)?$", "pageFamily": "dashboard", "heroTier": "tier4", "classificationSource": "pattern" },
  { "id": "auth", "match": "^/(login|sign-in|signup|auth|reset-password)(?:/.*)?$", "pageFamily": "auth", "heroTier": "tier4", "classificationSource": "pattern" },
  { "id": "blog-content", "match": "^/(blog|resources/legal|what-is|pilot-car-cost)(?:/.*)?$", "pageFamily": "glossary", "heroTier": "tier2", "classificationSource": "pattern" },
  { "id": "company-info", "match": "^/(about|how-it-works|contact|support|press|privacy|terms|security|content-policy|sla|trust|legal)(?:/.*)?$", "pageFamily": "utility", "heroTier": "tier4", "classificationSource": "pattern" },
  { "id": "search-answers", "match": "^/(search|answers|ai|chat|command|hq|library|playbook|developers)(?:/.*)?$", "pageFamily": "utility", "heroTier": "tier4", "classificationSource": "pattern" },
  { "id": "country-slugs", "match": "^/(canada|united-states)$", "pageFamily": "country", "heroTier": "tier1", "classificationSource": "pattern" },
  { "id": "escort-requirements", "match": "^/(escort-requirements|requirements|regulatory-db|regulatory-radar|permits)(?:/.*)?$", "pageFamily": "regulations", "heroTier": "tier1", "classificationSource": "pattern" },
  { "id": "market-intel", "match": "^/(data|markets|rate-index|shortage-index|insights|intelligence|intel|live-network)(?:/.*)?$", "pageFamily": "market-data", "heroTier": "tier2", "classificationSource": "pattern" },
  { "id": "load-actions", "match": "^/(availability|available-now-fixed|dispatch|emergency|post-a-load|request|quote|estimate|find-capacity|offers|messages|inbox|notifications)(?:/.*)?$", "pageFamily": "load-board", "heroTier": "tier2", "classificationSource": "pattern" },
  { "id": "role-directory-actions", "match": "^/(brokers|carrier|companies|providers|escort|find|reviews|verify|remove-listing)(?:/.*)?$", "pageFamily": "directory", "heroTier": "tier2", "classificationSource": "pattern" },
  { "id": "partner-growth", "match": "^/(careers|join|partner|partners|vendors|chambers)(?:/.*)?$", "pageFamily": "service", "heroTier": "tier2", "classificationSource": "pattern" },
  { "id": "commerce-utility", "match": "^/(ads|boost|checkout|download|plans|store|success|territory|upgrade|wallet|quickpay|escrow)(?:/.*)?$", "pageFamily": "pricing", "heroTier": "tier4", "classificationSource": "pattern" },
  { "id": "service-support", "match": "^/(compliance-kit|documents|equipment|fuel-cards|gear|industries|insurance|offline|reposition|repositioning|trucker-services|fleet)(?:/.*)?$", "pageFamily": "service", "heroTier": "tier2", "classificationSource": "pattern" },
  { "id": "route-crossings", "match": "^/(border|crossing|corridor-command|route-check|route|port)(?:/.*)?$", "pageFamily": "route-intel", "heroTier": "tier2", "classificationSource": "pattern" },
  { "id": "onboarding-auth", "match": "^/(onboarding|register|start|unsubscribe)(?:/.*)?$", "pageFamily": "auth", "heroTier": "tier4", "classificationSource": "pattern" },
  { "id": "comparison-pages", "match": "^/(vs|what-is-a-pilot-car|when-do-you-need-a-pilot-car)(?:/.*)?$", "pageFamily": "glossary", "heroTier": "tier2", "classificationSource": "pattern" },
  { "id": "homepage-aliases", "match": "^/(home|_seo_longtail_parked|dev)(?:/.*)?$", "pageFamily": "homepage", "heroTier": "tier4", "classificationSource": "pattern" },
  { "id": "enterprise-pages", "match": "^/enterprise(?:/.*)?$", "pageFamily": "service", "heroTier": "tier2", "classificationSource": "pattern" },
  { "id": "network-retention", "match": "^/(alerts|leaderboards|next-moves|referral)(?:/.*)?$", "pageFamily": "dashboard", "heroTier": "tier4", "classificationSource": "pattern" },
  { "id": "autonomous-freight", "match": "^/autonomous-freight(?:/.*)?$", "pageFamily": "route-intel", "heroTier": "tier2", "classificationSource": "pattern" },
  { "id": "proof-demo", "match": "^/demo-report-card(?:/.*)?$", "pageFamily": "profile", "heroTier": "tier3", "classificationSource": "pattern" },
  { "id": "icon-assets-page", "match": "^/icons(?:/.*)?$", "pageFamily": "utility", "heroTier": "tier4", "classificationSource": "pattern" },
  { "id": "fallback", "match": "^/.*$", "pageFamily": "utility", "heroTier": "tier4", "classificationSource": "fallback" }
]
